srcmap/__init__.py
srcmap/__version__.py
srcmap/direction/Arrow.png
srcmap/direction/ArrowRotateMap.png
srcmap/direction/ArrowRotateMapAll.png
srcmap/position/Amphoreus/Amphoreus_BloodbathedBattlefrontCastrumKremnos_F1OE.area.png
srcmap/position/Amphoreus/Amphoreus_BloodbathedBattlefrontCastrumKremnos_F1OE.feat.png
srcmap/position/Amphoreus/Amphoreus_BloodbathedBattlefrontCastrumKremnos_F1OE.png
srcmap/position/Amphoreus/Amphoreus_StrifeRuinsCastrumKremnos_F1OE.area.png
srcmap/position/Amphoreus/Amphoreus_StrifeRuinsCastrumKremnos_F1OE.feat.png
srcmap/position/Amphoreus/Amphoreus_StrifeRuinsCastrumKremnos_F1OE.png
srcmap/position/Herta/Herta_BaseZone.area.png
srcmap/position/Herta/Herta_BaseZone.feat.png
srcmap/position/Herta/Herta_BaseZone.png
srcmap/position/Herta/Herta_MasterControlZone.area.png
srcmap/position/Herta/Herta_MasterControlZone.feat.png
srcmap/position/Herta/Herta_MasterControlZone.png
srcmap/position/Herta/Herta_ParlorCar.area.png
srcmap/position/Herta/Herta_ParlorCar.feat.png
srcmap/position/Herta/Herta_ParlorCar.png
srcmap/position/Herta/Herta_StorageZone_B1.area.png
srcmap/position/Herta/Herta_StorageZone_B1.feat.png
srcmap/position/Herta/Herta_StorageZone_B1.png
srcmap/position/Herta/Herta_StorageZone_F1.area.png
srcmap/position/Herta/Herta_StorageZone_F1.feat.png
srcmap/position/Herta/Herta_StorageZone_F1.png
srcmap/position/Herta/Herta_StorageZone_F2.area.png
srcmap/position/Herta/Herta_StorageZone_F2.feat.png
srcmap/position/Herta/Herta_StorageZone_F2.png
srcmap/position/Herta/Herta_StorageZone_F2Rogue.area.png
srcmap/position/Herta/Herta_StorageZone_F2Rogue.feat.png
srcmap/position/Herta/Herta_StorageZone_F2Rogue.png
srcmap/position/Herta/Herta_SupplyZone_F1.area.png
srcmap/position/Herta/Herta_SupplyZone_F1.feat.png
srcmap/position/Herta/Herta_SupplyZone_F1.png
srcmap/position/Herta/Herta_SupplyZone_F2.area.png
srcmap/position/Herta/Herta_SupplyZone_F2.feat.png
srcmap/position/Herta/Herta_SupplyZone_F2.png
srcmap-3.2.20250422.dist-info/LICENSE
srcmap-3.2.20250422.dist-info/METADATA
srcmap-3.2.20250422.dist-info/WHEEL
srcmap-3.2.20250422.dist-info/top_level.txt
srcmap-3.2.20250422.dist-info/RECORD
