Metadata-Version: 2.1
Name: srcmap
Version: 3.2.20250422
Summary: Map data for StarRailCopilot
Home-page: https://github.com/LmeSzinc/SRCMAP
Author: LmeSzinc
Author-email: lmeszincsales@gamil.com
License: UNKNOWN
Platform: python3
Classifier: Programming Language :: Python :: 3
Requires-Python: >=3.7
License-File: LICENSE
